mypypioleksiivers4/__init__.py
mypypioleksiivers4/cli.py
mypypioleksiivers4/core.py
mypypioleksiivers4/data/1.txt
oleksiipypiexample_vers4-7.0.0.dist-info/METADATA
oleksiipypiexample_vers4-7.0.0.dist-info/WHEEL
oleksiipypiexample_vers4-7.0.0.dist-info/top_level.txt
oleksiipypiexample_vers4-7.0.0.dist-info/RECORD
