Metadata-Version: 2.4
Name: oleksiipypiexample-vers4
Version: 7.0.0
Summary: A simple pypi project to call a greeting function
Author-email: Oleksii Saiun <oleksiisaiun@example.com>
License: MIT
Requires-Python: >=3.10
